crypto_pair/__init__.py
crypto_pair/_lowlevel.py
crypto_pair/_lowlevel__ffi.py
crypto_pair/_lowlevel__lib.so
crypto_pair-2.3.11.dist-info/LICENSE
crypto_pair-2.3.11.dist-info/METADATA
crypto_pair-2.3.11.dist-info/WHEEL
crypto_pair-2.3.11.dist-info/top_level.txt
crypto_pair-2.3.11.dist-info/RECORD
crypto_pair.libs/libpcre-9513aab5.so.1.2.0
crypto_pair.libs/libkeyutils-dfe70bd6.so.1.5
crypto_pair.libs/libcom_err-2abe824b.so.2.1
crypto_pair.libs/libkrb5-fc820a1d.so.3.3
crypto_pair.libs/libselinux-0922c95c.so.1
crypto_pair.libs/libk5crypto-b1f99d5c.so.3.1
crypto_pair.libs/libkrb5support-a4e68a84.so.0.1
crypto_pair.libs/libcrypto-19957f5b.so.1.0.2k
crypto_pair.libs/libssl-2a9eae6f.so.1.0.2k
crypto_pair.libs/libgssapi_krb5-497db0c6.so.2.2
