Metadata-Version: 2.1
Name: crypto-pair
Version: 2.3.11
Summary: Normalize cryptocurrency trading pairs
Home-page: https://github.com/soulmachine/crypto-pair-py
Author: soulmachine
License: UNKNOWN
Keywords: blockchain,cryptocurrency,trading
Platform: UNKNOWN
Classifier: Programming Language :: Python :: 3.6
Classifier: License :: OSI Approved :: Apache Software License
Classifier: Topic :: Software Development :: Libraries :: Python Modules
Requires-Python: >=3.6
License-File: LICENSE
Requires-Dist: milksnake
